{
  "notes": [
    {
      "id": "3",
      "title": "Tailwind CSS",
      "content": "It is a utility first CSS framework. It is a very good alternative to Bootstrap. It is also very easy to learn and use.",
      "date": "2024-06-15",
      "tag": "css"
    },
    {
      "id": "4",
      "title": "Lucide",
      "content": "It is a icon collection. It is a very good alternative to Font Awesome. It is also very easy to learn and use.",
      "date": "2024-06-17",
      "tag": "icon"
    },
    {
      "id": "5",
      "title": "Vue Router",
      "content": "It is a client side router. It is a very good alternative to React Router. It is also very easy to learn and use.",
      "date": "2024-06-20",
      "tag": "vue"
    },
    {
      "title": "Vite updated",
      "content": "up It is a build tool. It is a very good alternative to Webpack. It is also very easy to learn and use.",
      "tag": "dev",
      "date": "2025-02-04",
      "id": "6"
    },
    {
      "id": "7",
      "title": "Vue 3",
      "content": "It is a JavaScript framework. It is a very good alternative to React. It is also very easy to learn and use.",
      "date": "2024-06-26",
      "tag": "vue"
    },
    {
      "id": "8",
      "title": "Vuetify",
      "content": "It is a UI framework. It is a very good alternative to Material Design. It is also very easy to learn and use.",
      "date": "2024-06-28",
      "tag": "vue"
    },
    {
      "id": "9",
      "title": "Vue CLI",
      "content": "It is a tool for generating Vue projects. It is a very good alternative to Create React App. It is also very easy to learn and use.",
      "date": "2024-06-30",
      "tag": "vue"
    },
    {
      "id": "10",
      "title": "Vue Devtools",
      "content": "It is a tool for debugging Vue projects. It is a very good alternative to React Devtools. It is also very easy to learn and use.",
      "date": "2024-07-01",
      "tag": "vue"
    }
  ],
  "tags": [
    {
      "id": "1",
      "name": "math"
    },
    {
      "id": "2",
      "name": "vue"
    },
    {
      "id": "3",
      "name": "css"
    },
    {
      "id": "4",
      "name": "icon"
    },
    {
      "id": "5",
      "name": "dev"
    }
  ]
}